[
  {
    "company": "Aufderhar-Ritchie",
    "position": "VP Quality Control",
    "jobLocation": "Tangzang",
    "jobType": "remote",
    "status": "pending",
    "createdBy": "",
    "createdAt": "2021-07-18T11:21:19Z"
  },
  {
    "company": "Pacocha Inc",
    "position": "Analyst Programmer",
    "jobLocation": "Soritor",
    "jobType": "remote",
    "status": "interview",
    "createdBy": "",
    "createdAt": "2021-02-12T16:56:33Z"
  },
  {
    "company": "Ondricka, Hyatt and Bode",
    "position": "Pharmacist",
    "jobLocation": "Hegarsari",
    "jobType": "remote",
    "status": "declined",
    "createdBy": "",
    "createdAt": "2020-08-05T19:01:47Z"
  },
  {
    "company": "Rowe LLC",
    "position": "Director of Sales",
    "jobLocation": "Tanlin",
    "jobType": "full-time",
    "status": "declined",
    "createdBy": "",
    "createdAt": "2021-03-31T22:26:35Z"
  },
  {
    "company": "Fahey, Langosh and Botsford",
    "position": "Assistant Professor",
    "jobLocation": "Sigeng",
    "jobType": "remote",
    "status": "declined",
    "createdBy": "",
    "createdAt": "2022-03-06T14:31:49Z"
  },
  {
    "company": "Sanford-Douglas",
    "position": "Quality Engineer",
    "jobLocation": "Puerto Plata",
    "jobType": "part-time",
    "status": "pending",
    "createdBy": "",
    "createdAt": "2020-01-04T04:40:26Z"
  },
  {
    "company": "Wisoky LLC",
    "position": "Structural Engineer",
    "jobLocation": "Hołoby",
    "jobType": "full-time",
    "status": "interview",
    "createdBy": "",
    "createdAt": "2021-03-09T21:02:17Z"
  },
  {
    "company": "Morissette, Koch and Hammes",
    "position": "Director of Sales",
    "jobLocation": "Liangshuihe",
    "jobType": "remote",
    "status": "declined",
    "createdBy": "",
    "createdAt": "2021-06-12T22:53:36Z"
  },
  {
    "company": "Metz Inc",
    "position": "Account Coordinator",
    "jobLocation": "Zahvizdya",
    "jobType": "remote",
    "status": "pending",
    "createdBy": "",
    "createdAt": "2021-08-16T22:40:05Z"
  },
  {
    "company": "Pacocha LLC",
    "position": "Staff Accountant II",
    "jobLocation": "Strizhi",
    "jobType": "intership",
    "status": "pending",
    "createdBy": "",
    "createdAt": "2021-03-16T03:36:56Z"
  },
  {
    "company": "Gibson Group",
    "position": "Account Coordinator",
    "jobLocation": "Ararat",
    "jobType": "full-time",
    "status": "declined",
    "createdBy": "",
    "createdAt": "2022-04-27T12:45:43Z"
  },
  {
    "company": "Lakin-Paucek",
    "position": "Quality Control Specialist",
    "jobLocation": "Lindesberg",
    "jobType": "remote",
    "status": "declined",
    "createdBy": "",
    "createdAt": "2021-11-26T09:39:00Z"
  },
  {
    "company": "Rohan LLC",
    "position": "Civil Engineer",
    "jobLocation": "Khorixas",
    "jobType": "part-time",
    "status": "pending",
    "createdBy": "",
    "createdAt": "2020-06-28T13:38:38Z"
  },
  {
    "company": "Emard Inc",
    "position": "VP Sales",
    "jobLocation": "Zhuravka",
    "jobType": "remote",
    "status": "declined",
    "createdBy": "",
    "createdAt": "2020-08-03T21:09:38Z"
  },
  {
    "company": "Wilderman Group",
    "position": "Software Test Engineer IV",
    "jobLocation": "Fendou",
    "jobType": "remote",
    "status": "pending",
    "createdBy": "",
    "createdAt": "2019-12-25T22:16:53Z"
  },
  {
    "company": "Lockman Inc",
    "position": "Environmental Specialist",
    "jobLocation": "Fuxi",
    "jobType": "remote",
    "status": "pending",
    "createdBy": "",
    "createdAt": "2019-11-30T17:15:01Z"
  },
  {
    "company": "Kassulke-Kub",
    "position": "Sales Representative",
    "jobLocation": "San Antonio",
    "jobType": "intership",
    "status": "pending",
    "createdBy": "",
    "createdAt": "2019-11-04T11:47:33Z"
  },
  {
    "company": "Kiehn, Beahan and Casper",
    "position": "Food Chemist",
    "jobLocation": "Jiuxian",
    "jobType": "full-time",
    "status": "pending",
    "createdBy": "",
    "createdAt": "2020-01-28T17:10:02Z"
  },
  {
    "company": "Nitzsche, Okuneva and Kilback",
    "position": "Associate Professor",
    "jobLocation": "Połomia",
    "jobType": "remote",
    "status": "pending",
    "createdBy": "",
    "createdAt": "2021-11-24T12:38:12Z"
  },
  {
    "company": "Flatley and Sons",
    "position": "Senior Cost Accountant",
    "jobLocation": "Pindamonhangaba",
    "jobType": "intership",
    "status": "pending",
    "createdBy": "",
    "createdAt": "2019-12-19T13:35:18Z"
  },
  {
    "company": "O'Kon-Abbott",
    "position": "Environmental Tech",
    "jobLocation": "Acacías",
    "jobType": "part-time",
    "status": "interview",
    "createdBy": "",
    "createdAt": "2022-02-27T21:16:35Z"
  },
  {
    "company": "Lynch, Abernathy and Kunde",
    "position": "Internal Auditor",
    "jobLocation": "Karanglincak",
    "jobType": "remote",
    "status": "declined",
    "createdBy": "",
    "createdAt": "2020-05-18T13:00:42Z"
  },
  {
    "company": "Wilkinson, Keeling and Anderson",
    "position": "Human Resources Assistant II",
    "jobLocation": "Zhiryatino",
    "jobType": "full-time",
    "status": "pending",
    "createdBy": "",
    "createdAt": "2021-09-05T16:09:22Z"
  },
  {
    "company": "Schulist LLC",
    "position": "Database Administrator II",
    "jobLocation": "Xushangqiao",
    "jobType": "remote",
    "status": "interview",
    "createdBy": "",
    "createdAt": "2021-07-12T07:11:33Z"
  },
  {
    "company": "Dietrich-Balistreri",
    "position": "Community Outreach Specialist",
    "jobLocation": "Vila Franca da Beira",
    "jobType": "intership",
    "status": "interview",
    "createdBy": "",
    "createdAt": "2021-03-09T15:02:39Z"
  },
  {
    "company": "Lang Group",
    "position": "Quality Engineer",
    "jobLocation": "Damu",
    "jobType": "remote",
    "status": "interview",
    "createdBy": "",
    "createdAt": "2020-12-25T01:59:45Z"
  },
  {
    "company": "Corkery Group",
    "position": "Cost Accountant",
    "jobLocation": "Duncan",
    "jobType": "intership",
    "status": "declined",
    "createdBy": "",
    "createdAt": "2020-05-01T02:41:25Z"
  },
  {
    "company": "Schaefer-Hackett",
    "position": "Developer II",
    "jobLocation": "Vårgårda",
    "jobType": "remote",
    "status": "declined",
    "createdBy": "",
    "createdAt": "2021-05-17T02:41:37Z"
  },
  {
    "company": "Reinger-Kemmer",
    "position": "Media Manager IV",
    "jobLocation": "Sapol",
    "jobType": "part-time",
    "status": "declined",
    "createdBy": "",
    "createdAt": "2020-04-24T12:39:03Z"
  },
  {
    "company": "Wolf, Shanahan and Friesen",
    "position": "Structural Analysis Engineer",
    "jobLocation": "Beizhang",
    "jobType": "intership",
    "status": "interview",
    "createdBy": "",
    "createdAt": "2020-12-08T20:56:52Z"
  },
  {
    "company": "Ankunding Group",
    "position": "Analyst Programmer",
    "jobLocation": "Derhachi",
    "jobType": "part-time",
    "status": "declined",
    "createdBy": "",
    "createdAt": "2020-05-11T23:01:50Z"
  },
  {
    "company": "Ernser-Schumm",
    "position": "Chemical Engineer",
    "jobLocation": "Vilque Chico",
    "jobType": "part-time",
    "status": "declined",
    "createdBy": "",
    "createdAt": "2022-01-30T14:13:09Z"
  },
  {
    "company": "Brakus-Bauch",
    "position": "Web Designer IV",
    "jobLocation": "Bayanhongor",
    "jobType": "part-time",
    "status": "pending",
    "createdBy": "",
    "createdAt": "2022-03-28T08:33:21Z"
  },
  {
    "company": "Kertzmann-DuBuque",
    "position": "Quality Engineer",
    "jobLocation": "Bayt ‘Ūr at Taḩtā",
    "jobType": "intership",
    "status": "pending",
    "createdBy": "",
    "createdAt": "2021-09-30T09:14:13Z"
  },
  {
    "company": "Kuvalis, Weissnat and Wintheiser",
    "position": "Occupational Therapist",
    "jobLocation": "Profítis Ilías",
    "jobType": "intership",
    "status": "declined",
    "createdBy": "",
    "createdAt": "2021-10-04T08:21:34Z"
  },
  {
    "company": "Walter LLC",
    "position": "Senior Cost Accountant",
    "jobLocation": "Huangjin",
    "jobType": "intership",
    "status": "declined",
    "createdBy": "",
    "createdAt": "2021-06-23T22:03:56Z"
  },
  {
    "company": "Stroman LLC",
    "position": "Administrative Officer",
    "jobLocation": "Ku‘aydinah",
    "jobType": "remote",
    "status": "pending",
    "createdBy": "",
    "createdAt": "2020-08-28T05:23:39Z"
  },
  {
    "company": "Ferry, Klocko and Abernathy",
    "position": "Systems Administrator IV",
    "jobLocation": "Novoselë",
    "jobType": "full-time",
    "status": "interview",
    "createdBy": "",
    "createdAt": "2019-11-15T11:16:04Z"
  },
  {
    "company": "Yost, Weimann and Hauck",
    "position": "Speech Pathologist",
    "jobLocation": "Puerto de Nutrias",
    "jobType": "part-time",
    "status": "pending",
    "createdBy": "",
    "createdAt": "2021-05-14T21:18:16Z"
  },
  {
    "company": "Mills Group",
    "position": "Accountant I",
    "jobLocation": "Lizhuang",
    "jobType": "intership",
    "status": "interview",
    "createdBy": "",
    "createdAt": "2022-09-19T21:56:11Z"
  }
]
